ytb.py
ytb-0.2.0.dist-info/DESCRIPTION.rst
ytb-0.2.0.dist-info/METADATA
ytb-0.2.0.dist-info/RECORD
ytb-0.2.0.dist-info/WHEEL
ytb-0.2.0.dist-info/entry_points.txt
ytb-0.2.0.dist-info/metadata.json
ytb-0.2.0.dist-info/top_level.txt
