Metadata-Version: 2.0
Name: ytb
Version: 0.2.0
Summary: download youtube use youtube-dl,more conventions
Home-page: https://github.com/hackrole/ytb
Author: hackrole
Author-email: hack.role@gmail.com
License: MIT
Keywords: youtube downloader
Platform: unix
Platform: macos
Requires-Python: >=3.5
Requires-Dist: Click
